python_baserow_simple/__init__.py
python_baserow_simple/__main__.py
python_baserow_simple/base.py
python_baserow_simple/cli.py
python_baserow_simple-0.0.4.dist-info/LICENSE
python_baserow_simple-0.0.4.dist-info/METADATA
python_baserow_simple-0.0.4.dist-info/WHEEL
python_baserow_simple-0.0.4.dist-info/entry_points.txt
python_baserow_simple-0.0.4.dist-info/top_level.txt
python_baserow_simple-0.0.4.dist-info/RECORD
