Metadata-Version: 2.1
Name: python-baserow-simple
Version: 0.0.4
Summary: Awesome python_baserow_simple created by xiamaz
Home-page: https://github.com/xiamaz/python-baserow-simple/
Author: xiamaz
License-File: LICENSE
Requires-Dist: requests
Provides-Extra: test
Requires-Dist: pytest ; extra == 'test'
Requires-Dist: coverage ; extra == 'test'
Requires-Dist: flake8 ; extra == 'test'
Requires-Dist: black ; extra == 'test'
Requires-Dist: isort ; extra == 'test'
Requires-Dist: pytest-cov ; extra == 'test'
Requires-Dist: codecov ; extra == 'test'
Requires-Dist: mypy ; extra == 'test'
Requires-Dist: gitchangelog ; extra == 'test'
Requires-Dist: mkdocs ; extra == 'test'
Requires-Dist: pyright ; extra == 'test'
Requires-Dist: ipython ; extra == 'test'
Requires-Dist: types-requests ; extra == 'test'
